{
  "@type" : "TEMPLATE",
  "uid" : "4f9a5b8c-37e6-4027-929a-1ab779cc7711",
  "description" : {
    "@type" : "RESOURCE_DESCRIPTION",
    "originalAuthor" : {
      "name" : "Vanessa Pereira",
      "organisation" : "Luxembourg Institute of Health (LIH)",
      "email" : "vanessapereira@pm.me",
      "date" : "2024-02-01"
    },
    "otherContributors" : [ ],
    "lifecycleState" : {
      "codeString" : "unmanaged"
    },
    "ipAcknowledgements" : { },
    "references" : { },
    "conversionDetails" : { },
    "otherDetails" : {
      "licence" : "",
      "custodian_organisation" : "",
      "original_namespace" : "",
      "original_publisher" : "",
      "custodian_namespace" : "",
      "sem_ver" : "0.1.0",
      "build_uid" : "c8bf2dfb-8c76-4fe7-8bd7-300eff04f8e3",
      "MD5-CAM-1.0.1" : "3ada8121907584fff23a2d7352d93a63",
      "PARENT:MD5-CAM-1.0.1" : "93D7156AD670461B54017CE2CB55ECAF"
    },
    "details" : {
      "nn" : {
        "@type" : "RESOURCE_DESCRIPTION_ITEM",
        "language" : {
          "terminologyId" : {
            "value" : "ISO_639-1"
          },
          "codeString" : "nn"
        },
        "keywords" : [ ],
        "originalResourceUri" : { },
        "otherDetails" : { }
      },
      "de" : {
        "@type" : "RESOURCE_DESCRIPTION_ITEM",
        "language" : {
          "terminologyId" : {
            "value" : "ISO_639-1"
          },
          "codeString" : "de"
        },
        "keywords" : [ ],
        "originalResourceUri" : { },
        "otherDetails" : { }
      },
      "sv" : {
        "@type" : "RESOURCE_DESCRIPTION_ITEM",
        "language" : {
          "terminologyId" : {
            "value" : "ISO_639-1"
          },
          "codeString" : "sv"
        },
        "keywords" : [ ],
        "originalResourceUri" : { },
        "otherDetails" : { }
      },
      "pt" : {
        "@type" : "RESOURCE_DESCRIPTION_ITEM",
        "language" : {
          "terminologyId" : {
            "value" : "ISO_639-1"
          },
          "codeString" : "pt"
        },
        "keywords" : [ ],
        "originalResourceUri" : { },
        "otherDetails" : { }
      },
      "nb" : {
        "@type" : "RESOURCE_DESCRIPTION_ITEM",
        "language" : {
          "terminologyId" : {
            "value" : "ISO_639-1"
          },
          "codeString" : "nb"
        },
        "keywords" : [ ],
        "originalResourceUri" : { },
        "otherDetails" : { }
      },
      "en" : {
        "@type" : "RESOURCE_DESCRIPTION_ITEM",
        "language" : {
          "terminologyId" : {
            "value" : "ISO_639-1"
          },
          "codeString" : "en"
        },
        "keywords" : [ ],
        "originalResourceUri" : { },
        "otherDetails" : { }
      },
      "fr" : {
        "@type" : "RESOURCE_DESCRIPTION_ITEM",
        "language" : {
          "terminologyId" : {
            "value" : "ISO_639-1"
          },
          "codeString" : "fr"
        },
        "keywords" : [ ],
        "originalResourceUri" : { },
        "otherDetails" : { }
      }
    }
  },
  "parentArchetypeId" : "openEHR-EHR-COMPOSITION.self_reported_data.v1",
  "differential" : true,
  "archetypeId" : {
    "@type" : "ARCHETYPE_HRID",
    "value" : "openEHR-EHR-COMPOSITION.t_self_reported_data.v1"
  },
  "definition" : {
    "@type" : "C_COMPLEX_OBJECT",
    "rmTypeName" : "COMPOSITION",
    "nodeId" : "at0000.1",
    "attributes" : [ {
      "@type" : "C_ATTRIBUTE",
      "rmAttributeName" : "context",
      "children" : [ {
        "@type" : "C_COMPLEX_OBJECT",
        "rmTypeName" : "EVENT_CONTEXT",
        "attributes" : [ ],
        "attributeTuples" : [ ]
      } ]
    }, {
      "@type" : "C_ATTRIBUTE",
      "rmAttributeName" : "content",
      "existence" : "0..1",
      "cardinality" : {
        "@type" : "CARDINALITY",
        "interval" : "1..*",
        "ordered" : false,
        "unique" : false
      },
      "children" : [ {
        "@type" : "C_ARCHETYPE_ROOT",
        "rmTypeName" : "OBSERVATION",
        "occurrences" : "0..1",
        "nodeId" : "at0.2",
        "attributes" : [ ],
        "attributeTuples" : [ ],
        "archetypeRef" : "openEHR-EHR-OBSERVATION.ovl-symptom_sign_screening-001.v1",
        "referenceType" : "archetypeOverlay"
      }, {
        "@type" : "C_ARCHETYPE_ROOT",
        "rmTypeName" : "OBSERVATION",
        "occurrences" : "0..1",
        "nodeId" : "at0.4",
        "attributes" : [ ],
        "attributeTuples" : [ ],
        "archetypeRef" : "openEHR-EHR-OBSERVATION.ovl-pain_scale-001.v1",
        "referenceType" : "archetypeOverlay"
      } ]
    } ],
    "attributeTuples" : [ ]
  },
  "terminology" : {
    "@type" : "ARCHETYPE_TERMINOLOGY",
    "conceptCode" : "at0000",
    "termDefinitions" : {
      "en" : {
        "at0000.1" : {
          "@type" : "ARCHETYPE_TERM",
          "code" : "at0000.1",
          "text" : "PIANISSIMO - Pain assessment",
          "description" : "Generic container for information provided by an individual."
        }
      },
      "nb" : {
        "at0000.1" : {
          "@type" : "ARCHETYPE_TERM",
          "code" : "at0000.1",
          "text" : "PIANISSIMO - Pain assessment",
          "description" : "Generisk container for informasjon gitt av et individ."
        }
      },
      "nn" : {
        "at0000.1" : {
          "@type" : "ARCHETYPE_TERM",
          "code" : "at0000.1",
          "text" : "PIANISSIMO - Pain assessment",
          "description" : "*Generic container for information provided by an individual. (en)"
        }
      },
      "sv" : {
        "at0000.1" : {
          "@type" : "ARCHETYPE_TERM",
          "code" : "at0000.1",
          "text" : "PIANISSIMO - Pain assessment",
          "description" : "Generell behållare för information som tillhandahålls av en individ."
        }
      },
      "de" : {
        "at0000.1" : {
          "@type" : "ARCHETYPE_TERM",
          "code" : "at0000.1",
          "text" : "PIANISSIMO - Pain assessment",
          "description" : "Generischer Container für Informationen, die von einer Person bereitgestellt werden."
        }
      },
      "fr" : {
        "at0000.1" : {
          "@type" : "ARCHETYPE_TERM",
          "code" : "at0000.1",
          "text" : "PIANISSIMO - Pain assessment",
          "description" : "Conteneur générique pour des informations fournies par un individu."
        }
      },
      "pt" : {
        "at0000.1" : {
          "@type" : "ARCHETYPE_TERM",
          "code" : "at0000.1",
          "text" : "PIANISSIMO - Pain assessment",
          "description" : "Contentor genérico para informação fornecida por um indivíduo."
        }
      }
    },
    "termBindings" : { },
    "terminologyExtracts" : { },
    "valueSets" : { }
  },
  "adlVersion" : "1.4",
  "buildUid" : "cb4a8c15-317d-36da-a0e2-b8b17a32f0f0",
  "rmName" : "openehr",
  "rmRelease" : "1.1.0",
  "generated" : true,
  "templateId" : "PIANISSIMO - Pain assessment",
  "otherMetaData" : { },
  "templateOverlays" : [ {
    "@type" : "TEMPLATE_OVERLAY",
    "uid" : "1ecd3534-8cf6-4791-a9eb-41a31aacd6e9",
    "description" : {
      "@type" : "RESOURCE_DESCRIPTION",
      "originalAuthor" : { },
      "otherContributors" : [ ],
      "ipAcknowledgements" : { },
      "references" : { },
      "conversionDetails" : { },
      "otherDetails" : {
        "PARENT:MD5-CAM-1.0.1" : "CFAA5A21F30725BDA8D018E31997EA7A"
      },
      "details" : { }
    },
    "parentArchetypeId" : "openEHR-EHR-OBSERVATION.symptom_sign_screening.v1",
    "differential" : true,
    "archetypeId" : {
      "@type" : "ARCHETYPE_HRID",
      "value" : "openEHR-EHR-OBSERVATION.ovl-symptom_sign_screening-001.v1"
    },
    "definition" : {
      "@type" : "C_COMPLEX_OBJECT",
      "rmTypeName" : "OBSERVATION",
      "nodeId" : "at0000.1",
      "attributes" : [ {
        "@type" : "C_ATTRIBUTE",
        "rmAttributeName" : "data",
        "children" : [ {
          "@type" : "C_COMPLEX_OBJECT",
          "rmTypeName" : "HISTORY",
          "nodeId" : "at0001",
          "attributes" : [ {
            "@type" : "C_ATTRIBUTE",
            "rmAttributeName" : "events",
            "children" : [ {
              "@type" : "C_COMPLEX_OBJECT",
              "rmTypeName" : "EVENT",
              "nodeId" : "at0002",
              "attributes" : [ {
                "@type" : "C_ATTRIBUTE",
                "rmAttributeName" : "data",
                "children" : [ {
                  "@type" : "C_COMPLEX_OBJECT",
                  "rmTypeName" : "ITEM_TREE",
                  "nodeId" : "at0003",
                  "attributes" : [ {
                    "@type" : "C_ATTRIBUTE",
                    "rmAttributeName" : "items",
                    "children" : [ {
                      "@type" : "C_COMPLEX_OBJECT",
                      "rmTypeName" : "ELEMENT",
                      "occurrences" : "0..0",
                      "nodeId" : "at0034.1",
                      "attributes" : [ ],
                      "attributeTuples" : [ ]
                    }, {
                      "@type" : "C_COMPLEX_OBJECT",
                      "rmTypeName" : "ELEMENT",
                      "occurrences" : "0..0",
                      "nodeId" : "at0028.1",
                      "attributes" : [ {
                        "@type" : "C_ATTRIBUTE",
                        "rmAttributeName" : "value",
                        "children" : [ {
                          "@type" : "C_COMPLEX_OBJECT",
                          "rmTypeName" : "DV_CODED_TEXT",
                          "attributes" : [ {
                            "@type" : "C_ATTRIBUTE",
                            "rmAttributeName" : "defining_code",
                            "children" : [ {
                              "@type" : "C_TERMINOLOGY_CODE",
                              "rmTypeName" : "TERMINOLOGY_CODE",
                              "occurrences" : "1..1",
                              "terminologyId" : {
                                "value" : "local"
                              },
                              "constraint" : [ "ac0.1" ],
                              "selectedTerminologies" : [ ]
                            } ]
                          } ],
                          "attributeTuples" : [ ]
                        }, {
                          "@type" : "C_COMPLEX_OBJECT",
                          "rmTypeName" : "DV_TEXT",
                          "attributes" : [ ],
                          "attributeTuples" : [ ]
                        }, {
                          "@type" : "C_COMPLEX_OBJECT",
                          "rmTypeName" : "DV_BOOLEAN",
                          "attributes" : [ ],
                          "attributeTuples" : [ ]
                        } ]
                      } ],
                      "attributeTuples" : [ ]
                    }, {
                      "@type" : "C_COMPLEX_OBJECT",
                      "rmTypeName" : "ELEMENT",
                      "occurrences" : "0..0",
                      "nodeId" : "at0029.1",
                      "attributes" : [ {
                        "@type" : "C_ATTRIBUTE",
                        "rmAttributeName" : "value",
                        "children" : [ {
                          "@type" : "C_COMPLEX_OBJECT",
                          "rmTypeName" : "DV_DATE_TIME",
                          "attributes" : [ ],
                          "attributeTuples" : [ ]
                        }, {
                          "@type" : "C_COMPLEX_OBJECT",
                          "rmTypeName" : "DV_INTERVAL<DV_DATE_TIME>",
                          "attributes" : [ ],
                          "attributeTuples" : [ ]
                        }, {
                          "@type" : "C_COMPLEX_OBJECT",
                          "rmTypeName" : "DV_TEXT",
                          "attributes" : [ ],
                          "attributeTuples" : [ ]
                        }, {
                          "@type" : "C_COMPLEX_OBJECT",
                          "rmTypeName" : "DV_DURATION",
                          "attributes" : [ ],
                          "attributeTuples" : [ ]
                        }, {
                          "@type" : "C_COMPLEX_OBJECT",
                          "rmTypeName" : "DV_INTERVAL<DV_DURATION>",
                          "attributes" : [ ],
                          "attributeTuples" : [ ]
                        } ]
                      } ],
                      "attributeTuples" : [ ]
                    }, {
                      "@type" : "C_COMPLEX_OBJECT",
                      "rmTypeName" : "ELEMENT",
                      "occurrences" : "0..0",
                      "nodeId" : "at0036.1",
                      "attributes" : [ ],
                      "attributeTuples" : [ ]
                    }, {
                      "@type" : "C_COMPLEX_OBJECT",
                      "rmTypeName" : "CLUSTER",
                      "occurrences" : "0..1",
                      "nodeId" : "at0022.1",
                      "attributes" : [ {
                        "@type" : "C_ATTRIBUTE",
                        "rmAttributeName" : "items",
                        "children" : [ {
                          "@type" : "C_COMPLEX_OBJECT",
                          "rmTypeName" : "ELEMENT",
                          "nodeId" : "at0004.1",
                          "attributes" : [ {
                            "@type" : "C_ATTRIBUTE",
                            "rmAttributeName" : "value",
                            "children" : [ {
                              "@type" : "C_COMPLEX_OBJECT",
                              "rmTypeName" : "DV_CODED_TEXT",
                              "occurrences" : "1..1",
                              "attributes" : [ {
                                "@type" : "C_ATTRIBUTE",
                                "rmAttributeName" : "defining_code",
                                "children" : [ {
                                  "@type" : "C_TERMINOLOGY_CODE",
                                  "rmTypeName" : "TERMINOLOGY_CODE",
                                  "occurrences" : "0..1",
                                  "terminologyId" : {
                                    "value" : "SNOMED-CT"
                                  },
                                  "constraint" : [ ],
                                  "selectedTerminologies" : [ "SNOMED-CT" ],
                                  "includedExternalTerminologyCodes" : [ {
                                    "terminologyId" : "SNOMED-CT",
                                    "code" : "57676002",
                                    "value" : "Joint pain"
                                  } ]
                                } ]
                              } ],
                              "attributeTuples" : [ ]
                            } ]
                          } ],
                          "attributeTuples" : [ ]
                        }, {
                          "@type" : "C_COMPLEX_OBJECT",
                          "rmTypeName" : "ELEMENT",
                          "occurrences" : "0..0",
                          "nodeId" : "at0005.1",
                          "attributes" : [ {
                            "@type" : "C_ATTRIBUTE",
                            "rmAttributeName" : "value",
                            "children" : [ {
                              "@type" : "C_COMPLEX_OBJECT",
                              "rmTypeName" : "DV_CODED_TEXT",
                              "attributes" : [ {
                                "@type" : "C_ATTRIBUTE",
                                "rmAttributeName" : "defining_code",
                                "children" : [ {
                                  "@type" : "C_TERMINOLOGY_CODE",
                                  "rmTypeName" : "TERMINOLOGY_CODE",
                                  "occurrences" : "1..1",
                                  "terminologyId" : {
                                    "value" : "local"
                                  },
                                  "constraint" : [ "ac0.2" ],
                                  "selectedTerminologies" : [ ]
                                } ]
                              } ],
                              "attributeTuples" : [ ]
                            }, {
                              "@type" : "C_COMPLEX_OBJECT",
                              "rmTypeName" : "DV_TEXT",
                              "attributes" : [ ],
                              "attributeTuples" : [ ]
                            }, {
                              "@type" : "C_COMPLEX_OBJECT",
                              "rmTypeName" : "DV_BOOLEAN",
                              "attributes" : [ ],
                              "attributeTuples" : [ ]
                            } ]
                          } ],
                          "attributeTuples" : [ ]
                        }, {
                          "@type" : "C_COMPLEX_OBJECT",
                          "rmTypeName" : "ELEMENT",
                          "occurrences" : "0..0",
                          "nodeId" : "at0037.1",
                          "attributes" : [ {
                            "@type" : "C_ATTRIBUTE",
                            "rmAttributeName" : "value",
                            "children" : [ {
                              "@type" : "C_COMPLEX_OBJECT",
                              "rmTypeName" : "DV_DURATION",
                              "attributes" : [ ],
                              "attributeTuples" : [ ]
                            }, {
                              "@type" : "C_COMPLEX_OBJECT",
                              "rmTypeName" : "DV_INTERVAL<DV_DURATION>",
                              "attributes" : [ ],
                              "attributeTuples" : [ ]
                            }, {
                              "@type" : "C_COMPLEX_OBJECT",
                              "rmTypeName" : "DV_DATE_TIME",
                              "attributes" : [ ],
                              "attributeTuples" : [ ]
                            }, {
                              "@type" : "C_COMPLEX_OBJECT",
                              "rmTypeName" : "DV_INTERVAL<DV_DATE_TIME>",
                              "attributes" : [ ],
                              "attributeTuples" : [ ]
                            }, {
                              "@type" : "C_COMPLEX_OBJECT",
                              "rmTypeName" : "DV_TEXT",
                              "attributes" : [ ],
                              "attributeTuples" : [ ]
                            } ]
                          } ],
                          "attributeTuples" : [ ]
                        }, {
                          "@type" : "C_COMPLEX_OBJECT",
                          "rmTypeName" : "ELEMENT",
                          "occurrences" : "0..0",
                          "nodeId" : "at0035.1",
                          "attributes" : [ ],
                          "attributeTuples" : [ ]
                        }, {
                          "@type" : "C_ARCHETYPE_ROOT",
                          "rmTypeName" : "CLUSTER",
                          "occurrences" : "0..*",
                          "nodeId" : "at0026.1",
                          "attributes" : [ ],
                          "attributeTuples" : [ ],
                          "archetypeRef" : "openEHR-EHR-CLUSTER.ovl-anatomical_location-001.v1",
                          "referenceType" : "archetypeOverlay"
                        }, {
                          "@type" : "C_ARCHETYPE_ROOT",
                          "rmTypeName" : "CLUSTER",
                          "occurrences" : "0..1",
                          "nodeId" : "at0026.2",
                          "attributes" : [ ],
                          "attributeTuples" : [ ],
                          "archetypeRef" : "openEHR-EHR-CLUSTER.ovl-timing_daily-001.v1",
                          "referenceType" : "archetypeOverlay"
                        } ]
                      } ],
                      "attributeTuples" : [ ]
                    } ]
                  } ],
                  "attributeTuples" : [ ]
                } ]
              } ],
              "attributeTuples" : [ ]
            } ]
          } ],
          "attributeTuples" : [ ]
        } ]
      } ],
      "attributeTuples" : [ ]
    },
    "terminology" : {
      "@type" : "ARCHETYPE_TERMINOLOGY",
      "conceptCode" : "at0000",
      "termDefinitions" : {
        "en" : {
          "ac0.1" : {
            "@type" : "ARCHETYPE_TERM",
            "text" : "(Synthesized)",
            "code" : "ac0.1",
            "description" : ""
          },
          "ac0.2" : {
            "@type" : "ARCHETYPE_TERM",
            "text" : "(Synthesized)",
            "code" : "ac0.2",
            "description" : ""
          }
        },
        "fi" : {
          "ac0.1" : {
            "@type" : "ARCHETYPE_TERM",
            "text" : "*(Synthesized) (en)",
            "code" : "ac0.1",
            "description" : ""
          },
          "ac0.2" : {
            "@type" : "ARCHETYPE_TERM",
            "text" : "*(Synthesized) (en)",
            "code" : "ac0.2",
            "description" : ""
          }
        },
        "nb" : {
          "ac0.1" : {
            "@type" : "ARCHETYPE_TERM",
            "text" : "*(Synthesized) (en)",
            "code" : "ac0.1",
            "description" : ""
          },
          "ac0.2" : {
            "@type" : "ARCHETYPE_TERM",
            "text" : "*(Synthesized) (en)",
            "code" : "ac0.2",
            "description" : ""
          }
        },
        "de" : {
          "ac0.1" : {
            "@type" : "ARCHETYPE_TERM",
            "text" : "*(Synthesized) (en)",
            "code" : "ac0.1",
            "description" : ""
          },
          "ac0.2" : {
            "@type" : "ARCHETYPE_TERM",
            "text" : "*(Synthesized) (en)",
            "code" : "ac0.2",
            "description" : ""
          }
        },
        "it" : {
          "ac0.1" : {
            "@type" : "ARCHETYPE_TERM",
            "text" : "*(Synthesized) (en)",
            "code" : "ac0.1",
            "description" : ""
          },
          "ac0.2" : {
            "@type" : "ARCHETYPE_TERM",
            "text" : "*(Synthesized) (en)",
            "code" : "ac0.2",
            "description" : ""
          }
        },
        "sv" : {
          "ac0.1" : {
            "@type" : "ARCHETYPE_TERM",
            "text" : "*(Synthesized) (en)",
            "code" : "ac0.1",
            "description" : ""
          },
          "ac0.2" : {
            "@type" : "ARCHETYPE_TERM",
            "text" : "*(Synthesized) (en)",
            "code" : "ac0.2",
            "description" : ""
          }
        }
      },
      "termBindings" : { },
      "terminologyExtracts" : { },
      "valueSets" : {
        "ac0.1" : {
          "@type" : "VALUE_SET",
          "id" : "ac0.1",
          "members" : [ "at0031", "at0032", "at0033" ]
        },
        "ac0.2" : {
          "@type" : "VALUE_SET",
          "id" : "ac0.2",
          "members" : [ "at0023", "at0024", "at0027" ]
        }
      }
    },
    "adlVersion" : "1.4",
    "buildUid" : "cb339629-23a5-4417-991c-359fe3baea7e",
    "rmName" : "openehr",
    "rmRelease" : "1.1.0",
    "generated" : true,
    "otherMetaData" : { },
    "originalLanguage" : {
      "terminologyId" : {
        "value" : "ISO_639-1"
      },
      "codeString" : "en"
    },
    "translations" : [ {
      "@type" : "TRANSLATION_DETAILS",
      "language" : {
        "terminologyId" : {
          "value" : "ISO_639-1"
        },
        "codeString" : "de"
      },
      "author" : {
        "name" : "Sarah Ballout, Natalia Strauch",
        "organisation" : "Medizinische Hochschule Hannover",
        "email" : "ballout.sarah@mh-hannover.de, Strauch.Natalia@mh-hannover.de"
      },
      "otherDetails" : { }
    }, {
      "@type" : "TRANSLATION_DETAILS",
      "language" : {
        "terminologyId" : {
          "value" : "ISO_639-1"
        },
        "codeString" : "fi"
      },
      "author" : { },
      "otherDetails" : { }
    }, {
      "@type" : "TRANSLATION_DETAILS",
      "language" : {
        "terminologyId" : {
          "value" : "ISO_639-1"
        },
        "codeString" : "sv"
      },
      "author" : {
        "name" : "Emma Malm, Erik Sundvall",
        "organisation" : "Karolinska University Hospital, Region Stockholm, Karolinska University Hospital, Region Stockholm + Linköping University, Karolinska Institutet + Karolinska University Hospital, Region Stockholm + Linköping University",
        "email" : "emma.malm@cambio.se, erik.sundvall@regionstockholm.se"
      },
      "otherDetails" : { }
    }, {
      "@type" : "TRANSLATION_DETAILS",
      "language" : {
        "terminologyId" : {
          "value" : "ISO_639-1"
        },
        "codeString" : "nb"
      },
      "author" : {
        "name" : "Marit Alice Venheim, Silje Ljosland Bakke, John Tore Valand",
        "organisation" : "Helse Vest IKT AS, Helse Bergen",
        "email" : "marit.alice.venheim@helse-vest-ikt.no, silje.ljosland.bakke@helse-vest-ikt.no, john.tore.valand@helse-vest-ikt.no"
      },
      "otherDetails" : { }
    }, {
      "@type" : "TRANSLATION_DETAILS",
      "language" : {
        "terminologyId" : {
          "value" : "ISO_639-1"
        },
        "codeString" : "it"
      },
      "author" : { },
      "otherDetails" : { }
    } ]
  }, {
    "@type" : "TEMPLATE_OVERLAY",
    "uid" : "6d0fb192-297d-4d36-87f3-641cf9a9005f",
    "description" : {
      "@type" : "RESOURCE_DESCRIPTION",
      "originalAuthor" : { },
      "otherContributors" : [ ],
      "ipAcknowledgements" : { },
      "references" : { },
      "conversionDetails" : { },
      "otherDetails" : {
        "PARENT:MD5-CAM-1.0.1" : "62823A86BC1C2B02574125E21F5DECCB"
      },
      "details" : { }
    },
    "parentArchetypeId" : "openEHR-EHR-CLUSTER.anatomical_location.v1",
    "differential" : true,
    "archetypeId" : {
      "@type" : "ARCHETYPE_HRID",
      "value" : "openEHR-EHR-CLUSTER.ovl-anatomical_location-001.v1"
    },
    "definition" : {
      "@type" : "C_COMPLEX_OBJECT",
      "rmTypeName" : "CLUSTER",
      "nodeId" : "at0000.1",
      "attributes" : [ {
        "@type" : "C_ATTRIBUTE",
        "rmAttributeName" : "items",
        "children" : [ {
          "@type" : "C_COMPLEX_OBJECT",
          "rmTypeName" : "ELEMENT",
          "nodeId" : "at0001.1",
          "attributes" : [ {
            "@type" : "C_ATTRIBUTE",
            "rmAttributeName" : "value",
            "children" : [ {
              "@type" : "C_COMPLEX_OBJECT",
              "rmTypeName" : "DV_CODED_TEXT",
              "occurrences" : "1..1",
              "attributes" : [ {
                "@type" : "C_ATTRIBUTE",
                "rmAttributeName" : "defining_code",
                "children" : [ {
                  "@type" : "C_TERMINOLOGY_CODE",
                  "rmTypeName" : "TERMINOLOGY_CODE",
                  "occurrences" : "0..1",
                  "terminologyId" : {
                    "value" : "SNOMED-CT"
                  },
                  "constraint" : [ ],
                  "selectedTerminologies" : [ "SNOMED-CT" ],
                  "includedExternalTerminologyCodes" : [ {
                    "terminologyId" : "SNOMED-CT",
                    "code" : "53620006",
                    "value" : "Temporomandibular joint"
                  }, {
                    "terminologyId" : "SNOMED-CT",
                    "code" : "7844006",
                    "value" : "Sternoclavicular joint"
                  }, {
                    "terminologyId" : "SNOMED-CT",
                    "code" : "85856004",
                    "value" : "Acromioclavicular joint"
                  }, {
                    "terminologyId" : "SNOMED-CT",
                    "code" : "85537004",
                    "value" : "Glenohumeral joint"
                  }, {
                    "terminologyId" : "SNOMED-CT",
                    "code" : "16953009",
                    "value" : "Elbow joint"
                  }, {
                    "terminologyId" : "SNOMED-CT",
                    "code" : "74670003",
                    "value" : "Wrist joint"
                  }, {
                    "terminologyId" : "SNOMED-CT",
                    "code" : "56310002",
                    "value" : "Metacarpophalangeal joint structure of thumb"
                  }, {
                    "terminologyId" : "SNOMED-CT",
                    "code" : "289002",
                    "value" : "Metacarpophalangeal joint structure of index finger"
                  }, {
                    "terminologyId" : "SNOMED-CT",
                    "code" : "6059006",
                    "value" : "Metacarpophalangeal joint structure of middle finger"
                  }, {
                    "terminologyId" : "SNOMED-CT",
                    "code" : "13822002",
                    "value" : "Metacarpophalangeal joint structure of ring finger"
                  }, {
                    "terminologyId" : "SNOMED-CT",
                    "code" : "5493005",
                    "value" : "Metacarpophalangeal joint structure of little finger"
                  }, {
                    "terminologyId" : "SNOMED-CT",
                    "code" : "371218009",
                    "value" : "Distal interphalangeal joint of middle finger"
                  }, {
                    "terminologyId" : "SNOMED-CT",
                    "code" : "371210002",
                    "value" : "Distal interphalangeal joint of index finger"
                  }, {
                    "terminologyId" : "SNOMED-CT",
                    "code" : "371204002",
                    "value" : "Distal interphalangeal joint of ring finger"
                  }, {
                    "terminologyId" : "SNOMED-CT",
                    "code" : "371202003",
                    "value" : "Distal interphalangeal joint of little finger"
                  }, {
                    "terminologyId" : "SNOMED-CT",
                    "code" : "371263005",
                    "value" : "Proximal interphalangeal joint of middle finger"
                  }, {
                    "terminologyId" : "SNOMED-CT",
                    "code" : "371270005",
                    "value" : "Proximal interphalangeal joint of index finger"
                  }, {
                    "terminologyId" : "SNOMED-CT",
                    "code" : "371233001",
                    "value" : "Proximal interphalangeal joint of little finger"
                  }, {
                    "terminologyId" : "SNOMED-CT",
                    "code" : "371267006",
                    "value" : "Proximal interphalangeal joint of ring finger"
                  }, {
                    "terminologyId" : "SNOMED-CT",
                    "code" : "115955008",
                    "value" : "Interphalangeal joint of thumb"
                  }, {
                    "terminologyId" : "SNOMED-CT",
                    "code" : "24136001",
                    "value" : "Hip joint"
                  }, {
                    "terminologyId" : "SNOMED-CT",
                    "code" : "49076000",
                    "value" : "Knee joint"
                  }, {
                    "terminologyId" : "SNOMED-CT",
                    "code" : "70258002",
                    "value" : "Ankle joint"
                  }, {
                    "terminologyId" : "SNOMED-CT",
                    "code" : "26552008",
                    "value" : "Foot joint"
                  }, {
                    "terminologyId" : "SNOMED-CT",
                    "code" : "788338001",
                    "value" : "Entire midtarsal joint region"
                  }, {
                    "terminologyId" : "SNOMED-CT",
                    "code" : "27824001",
                    "value" : "Metatarsophalangeal joint of great toe"
                  }, {
                    "terminologyId" : "SNOMED-CT",
                    "code" : "71721008",
                    "value" : "Metatarsophalangeal joint structure of second toe"
                  }, {
                    "terminologyId" : "SNOMED-CT",
                    "code" : "81247008",
                    "value" : "Metatarsophalangeal joint structure of third toe"
                  }, {
                    "terminologyId" : "SNOMED-CT",
                    "code" : "45230000",
                    "value" : "Metatarsophalangeal joint structure of fourth toe"
                  }, {
                    "terminologyId" : "SNOMED-CT",
                    "code" : "50133002",
                    "value" : "Metatarsophalangeal joint structure of fifth toe"
                  }, {
                    "terminologyId" : "SNOMED-CT",
                    "code" : "1187457005",
                    "value" : "Proximal interphalangeal joint structure of lesser toe"
                  }, {
                    "terminologyId" : "SNOMED-CT",
                    "code" : "371292009",
                    "value" : "Proximal interphalangeal joint structure of second toe"
                  }, {
                    "terminologyId" : "SNOMED-CT",
                    "code" : "371255009",
                    "value" : "Proximal interphalangeal joint structure of third toe"
                  }, {
                    "terminologyId" : "SNOMED-CT",
                    "code" : "371288002",
                    "value" : "Proximal interphalangeal joint structure of fourth toe"
                  }, {
                    "terminologyId" : "SNOMED-CT",
                    "code" : "371284000",
                    "value" : "Proximal interphalangeal joint structure of fifth toe"
                  }, {
                    "terminologyId" : "SNOMED-CT",
                    "code" : "421060004",
                    "value" : "Structure of vertebral column"
                  } ]
                } ]
              } ],
              "attributeTuples" : [ ]
            } ]
          } ],
          "attributeTuples" : [ ]
        }, {
          "@type" : "C_COMPLEX_OBJECT",
          "rmTypeName" : "ELEMENT",
          "occurrences" : "0..0",
          "nodeId" : "at0065.1",
          "attributes" : [ ],
          "attributeTuples" : [ ]
        }, {
          "@type" : "C_COMPLEX_OBJECT",
          "rmTypeName" : "ELEMENT",
          "occurrences" : "0..0",
          "nodeId" : "at0064.1",
          "attributes" : [ {
            "@type" : "C_ATTRIBUTE",
            "rmAttributeName" : "value",
            "children" : [ {
              "@type" : "C_COMPLEX_OBJECT",
              "rmTypeName" : "DV_CODED_TEXT",
              "attributes" : [ {
                "@type" : "C_ATTRIBUTE",
                "rmAttributeName" : "defining_code",
                "children" : [ {
                  "@type" : "C_TERMINOLOGY_CODE",
                  "rmTypeName" : "TERMINOLOGY_CODE",
                  "occurrences" : "1..1",
                  "terminologyId" : {
                    "value" : "local"
                  },
                  "constraint" : [ "ac0.1" ],
                  "selectedTerminologies" : [ ]
                } ]
              } ],
              "attributeTuples" : [ ]
            }, {
              "@type" : "C_COMPLEX_OBJECT",
              "rmTypeName" : "DV_TEXT",
              "attributes" : [ ],
              "attributeTuples" : [ ]
            } ]
          } ],
          "attributeTuples" : [ ]
        }, {
          "@type" : "C_COMPLEX_OBJECT",
          "rmTypeName" : "ELEMENT",
          "occurrences" : "0..0",
          "nodeId" : "at0055.1",
          "attributes" : [ {
            "@type" : "C_ATTRIBUTE",
            "rmAttributeName" : "value",
            "children" : [ {
              "@type" : "C_COMPLEX_OBJECT",
              "rmTypeName" : "DV_CODED_TEXT",
              "attributes" : [ {
                "@type" : "C_ATTRIBUTE",
                "rmAttributeName" : "defining_code",
                "children" : [ {
                  "@type" : "C_TERMINOLOGY_CODE",
                  "rmTypeName" : "TERMINOLOGY_CODE",
                  "occurrences" : "1..1",
                  "terminologyId" : {
                    "value" : "local"
                  },
                  "constraint" : [ "ac0.2" ],
                  "selectedTerminologies" : [ ]
                } ]
              } ],
              "attributeTuples" : [ ]
            }, {
              "@type" : "C_COMPLEX_OBJECT",
              "rmTypeName" : "DV_TEXT",
              "attributes" : [ ],
              "attributeTuples" : [ ]
            } ]
          } ],
          "attributeTuples" : [ ]
        }, {
          "@type" : "C_COMPLEX_OBJECT",
          "rmTypeName" : "ELEMENT",
          "occurrences" : "0..0",
          "nodeId" : "at0023.1",
          "attributes" : [ ],
          "attributeTuples" : [ ]
        }, {
          "@type" : "C_ARCHETYPE_ROOT",
          "rmTypeName" : "CLUSTER",
          "occurrences" : "0..1",
          "nodeId" : "at0053.1",
          "attributes" : [ ],
          "attributeTuples" : [ ],
          "archetypeRef" : "openEHR-EHR-CLUSTER.ovl-range_of_motion-001.v1",
          "referenceType" : "archetypeOverlay"
        } ]
      } ],
      "attributeTuples" : [ ]
    },
    "terminology" : {
      "@type" : "ARCHETYPE_TERMINOLOGY",
      "conceptCode" : "at0000",
      "termDefinitions" : {
        "ar-sy" : {
          "ac0.1" : {
            "@type" : "ARCHETYPE_TERM",
            "text" : "*(Synthesized) (en)",
            "code" : "ac0.1",
            "description" : ""
          },
          "ac0.2" : {
            "@type" : "ARCHETYPE_TERM",
            "text" : "*(Synthesized) (en)",
            "code" : "ac0.2",
            "description" : ""
          }
        },
        "sl" : {
          "ac0.1" : {
            "@type" : "ARCHETYPE_TERM",
            "text" : "*(Synthesized) (en)",
            "code" : "ac0.1",
            "description" : ""
          },
          "ac0.2" : {
            "@type" : "ARCHETYPE_TERM",
            "text" : "*(Synthesized) (en)",
            "code" : "ac0.2",
            "description" : ""
          }
        },
        "en" : {
          "ac0.1" : {
            "@type" : "ARCHETYPE_TERM",
            "text" : "(Synthesized)",
            "code" : "ac0.1",
            "description" : ""
          },
          "ac0.2" : {
            "@type" : "ARCHETYPE_TERM",
            "text" : "(Synthesized)",
            "code" : "ac0.2",
            "description" : ""
          }
        },
        "nb" : {
          "ac0.1" : {
            "@type" : "ARCHETYPE_TERM",
            "text" : "*(Synthesized) (en)",
            "code" : "ac0.1",
            "description" : ""
          },
          "ac0.2" : {
            "@type" : "ARCHETYPE_TERM",
            "text" : "*(Synthesized) (en)",
            "code" : "ac0.2",
            "description" : ""
          }
        },
        "pt-br" : {
          "ac0.1" : {
            "@type" : "ARCHETYPE_TERM",
            "text" : "*(Synthesized) (en)",
            "code" : "ac0.1",
            "description" : ""
          },
          "ac0.2" : {
            "@type" : "ARCHETYPE_TERM",
            "text" : "*(Synthesized) (en)",
            "code" : "ac0.2",
            "description" : ""
          }
        },
        "de" : {
          "ac0.1" : {
            "@type" : "ARCHETYPE_TERM",
            "text" : "*(Synthesized) (en)",
            "code" : "ac0.1",
            "description" : ""
          },
          "ac0.2" : {
            "@type" : "ARCHETYPE_TERM",
            "text" : "*(Synthesized) (en)",
            "code" : "ac0.2",
            "description" : ""
          }
        },
        "nl" : {
          "ac0.1" : {
            "@type" : "ARCHETYPE_TERM",
            "text" : "*(Synthesized) (en)",
            "code" : "ac0.1",
            "description" : ""
          },
          "ac0.2" : {
            "@type" : "ARCHETYPE_TERM",
            "text" : "*(Synthesized) (en)",
            "code" : "ac0.2",
            "description" : ""
          }
        },
        "sv" : {
          "ac0.1" : {
            "@type" : "ARCHETYPE_TERM",
            "text" : "*(Synthesized) (en)",
            "code" : "ac0.1",
            "description" : ""
          },
          "ac0.2" : {
            "@type" : "ARCHETYPE_TERM",
            "text" : "*(Synthesized) (en)",
            "code" : "ac0.2",
            "description" : ""
          }
        }
      },
      "termBindings" : { },
      "terminologyExtracts" : { },
      "valueSets" : {
        "ac0.1" : {
          "@type" : "VALUE_SET",
          "id" : "ac0.1",
          "members" : [ "at0067", "at0068", "at0069", "at0070", "at0071", "at0072", "at0073", "at0074", "at0080", "at0081", "at0075", "at0076", "at0082", "at0077", "at0078", "at0079" ]
        },
        "ac0.2" : {
          "@type" : "VALUE_SET",
          "id" : "ac0.2",
          "members" : [ "at0062", "at0056", "at0057", "at0058", "at0059", "at0060", "at0063" ]
        }
      }
    },
    "adlVersion" : "1.4",
    "buildUid" : "13ee6d25-aa99-4221-bdc1-3c7ee7e58795",
    "rmName" : "openehr",
    "rmRelease" : "1.1.0",
    "generated" : true,
    "otherMetaData" : { },
    "originalLanguage" : {
      "terminologyId" : {
        "value" : "ISO_639-1"
      },
      "codeString" : "en"
    },
    "translations" : [ {
      "@type" : "TRANSLATION_DETAILS",
      "language" : {
        "terminologyId" : {
          "value" : "ISO_639-1"
        },
        "codeString" : "de"
      },
      "author" : {
        "name" : "Sarah Ballout",
        "email" : "ballout.sarah@mh-hannover.de"
      },
      "otherDetails" : { }
    }, {
      "@type" : "TRANSLATION_DETAILS",
      "language" : {
        "terminologyId" : {
          "value" : "ISO_639-1"
        },
        "codeString" : "sv"
      },
      "author" : {
        "name" : "Åsa Skagerhult, Linda Aulin",
        "organisation" : "Region Östergötland, Region Stockholm",
        "email" : "asa.skagerhult@regionostergotland.se, linda.aulin@sll.se"
      },
      "otherDetails" : { }
    }, {
      "@type" : "TRANSLATION_DETAILS",
      "language" : {
        "terminologyId" : {
          "value" : "ISO_639-1"
        },
        "codeString" : "nb"
      },
      "author" : {
        "name" : "Lars Bitsch-Larsen",
        "organisation" : "Haukeland University Hospital of Bergen, Norway"
      },
      "accreditation" : "MD, DEAA, MBA, spec in anesthesia, spec in tropical medicine.",
      "otherDetails" : { }
    }, {
      "@type" : "TRANSLATION_DETAILS",
      "language" : {
        "terminologyId" : {
          "value" : "ISO_639-1"
        },
        "codeString" : "pt-br"
      },
      "author" : {
        "name" : "Osmeire Chamelette Sanzovo",
        "organisation" : "Hospital Sírio Libanês - SP",
        "email" : "osmeire.acsanzovo@hsl.org.br"
      },
      "otherDetails" : { }
    }, {
      "@type" : "TRANSLATION_DETAILS",
      "language" : {
        "terminologyId" : {
          "value" : "ISO_639-1"
        },
        "codeString" : "ar-sy"
      },
      "author" : {
        "name" : "Mona Saleh"
      },
      "otherDetails" : { }
    }, {
      "@type" : "TRANSLATION_DETAILS",
      "language" : {
        "terminologyId" : {
          "value" : "ISO_639-1"
        },
        "codeString" : "sl"
      },
      "author" : {
        "name" : "Biljana Princic"
      },
      "otherDetails" : { }
    }, {
      "@type" : "TRANSLATION_DETAILS",
      "language" : {
        "terminologyId" : {
          "value" : "ISO_639-1"
        },
        "codeString" : "nl"
      },
      "author" : {
        "name" : "Michiel Klitsie",
        "organisation" : "Nedap Healthcare",
        "email" : "michiel.klitsie@nedap.com"
      },
      "otherDetails" : { }
    } ]
  }, {
    "@type" : "TEMPLATE_OVERLAY",
    "uid" : "ce20c0da-bfb3-4cdc-af1c-a128d9736751",
    "description" : {
      "@type" : "RESOURCE_DESCRIPTION",
      "originalAuthor" : { },
      "otherContributors" : [ ],
      "ipAcknowledgements" : { },
      "references" : { },
      "conversionDetails" : { },
      "otherDetails" : {
        "PARENT:MD5-CAM-1.0.1" : "66A281BF4B9267F94ADB6EBB312605E2"
      },
      "details" : { }
    },
    "parentArchetypeId" : "openEHR-EHR-OBSERVATION.pain_scale.v1",
    "differential" : true,
    "archetypeId" : {
      "@type" : "ARCHETYPE_HRID",
      "value" : "openEHR-EHR-OBSERVATION.ovl-pain_scale-001.v1"
    },
    "definition" : {
      "@type" : "C_COMPLEX_OBJECT",
      "rmTypeName" : "OBSERVATION",
      "nodeId" : "at0000.1",
      "attributes" : [ {
        "@type" : "C_ATTRIBUTE",
        "rmAttributeName" : "data",
        "children" : [ {
          "@type" : "C_COMPLEX_OBJECT",
          "rmTypeName" : "HISTORY",
          "nodeId" : "at0001",
          "attributes" : [ {
            "@type" : "C_ATTRIBUTE",
            "rmAttributeName" : "events",
            "children" : [ {
              "@type" : "C_COMPLEX_OBJECT",
              "rmTypeName" : "POINT_EVENT",
              "nodeId" : "at0002",
              "attributes" : [ {
                "@type" : "C_ATTRIBUTE",
                "rmAttributeName" : "data",
                "children" : [ {
                  "@type" : "C_COMPLEX_OBJECT",
                  "rmTypeName" : "ITEM_TREE",
                  "nodeId" : "at0003",
                  "attributes" : [ {
                    "@type" : "C_ATTRIBUTE",
                    "rmAttributeName" : "items",
                    "children" : [ {
                      "@type" : "C_COMPLEX_OBJECT",
                      "rmTypeName" : "ELEMENT",
                      "occurrences" : "0..0",
                      "nodeId" : "at0005.1",
                      "attributes" : [ ],
                      "attributeTuples" : [ ]
                    } ]
                  } ],
                  "attributeTuples" : [ ]
                } ]
              }, {
                "@type" : "C_ATTRIBUTE",
                "rmAttributeName" : "state",
                "children" : [ {
                  "@type" : "C_COMPLEX_OBJECT",
                  "rmTypeName" : "ITEM_TREE",
                  "nodeId" : "at0006",
                  "attributes" : [ {
                    "@type" : "C_ATTRIBUTE",
                    "rmAttributeName" : "items",
                    "children" : [ {
                      "@type" : "C_COMPLEX_OBJECT",
                      "rmTypeName" : "ELEMENT",
                      "occurrences" : "0..0",
                      "nodeId" : "at0007.1",
                      "attributes" : [ ],
                      "attributeTuples" : [ ]
                    } ]
                  } ],
                  "attributeTuples" : [ ]
                } ]
              } ],
              "attributeTuples" : [ ]
            } ]
          } ],
          "attributeTuples" : [ ]
        } ]
      } ],
      "attributeTuples" : [ ]
    },
    "terminology" : {
      "@type" : "ARCHETYPE_TERMINOLOGY",
      "conceptCode" : "at0000",
      "termDefinitions" : {
        "de" : { },
        "en" : { }
      },
      "termBindings" : { },
      "terminologyExtracts" : { },
      "valueSets" : { }
    },
    "adlVersion" : "1.4",
    "buildUid" : "252c6f14-400d-468a-8f60-53eb062e14b0",
    "rmName" : "openehr",
    "rmRelease" : "1.1.0",
    "generated" : true,
    "otherMetaData" : { },
    "originalLanguage" : {
      "terminologyId" : {
        "value" : "ISO_639-1"
      },
      "codeString" : "de"
    },
    "translations" : [ {
      "@type" : "TRANSLATION_DETAILS",
      "language" : {
        "terminologyId" : {
          "value" : "ISO_639-1"
        },
        "codeString" : "en"
      },
      "author" : {
        "name" : "Kristina Scheuermann",
        "organisation" : "Medizinische Hochschule Hannover (MHH)",
        "email" : "scheuermann.kristina@mh-hannover.de"
      },
      "otherDetails" : { }
    } ]
  }, {
    "@type" : "TEMPLATE_OVERLAY",
    "uid" : "7fa958b4-8ab4-4fd7-aa81-69a3d6562404",
    "description" : {
      "@type" : "RESOURCE_DESCRIPTION",
      "originalAuthor" : { },
      "otherContributors" : [ ],
      "ipAcknowledgements" : { },
      "references" : { },
      "conversionDetails" : { },
      "otherDetails" : {
        "PARENT:MD5-CAM-1.0.1" : "AFF2B50F9803DB3A81DE95E991760200"
      },
      "details" : { }
    },
    "parentArchetypeId" : "openEHR-EHR-CLUSTER.range_of_motion.v1",
    "differential" : true,
    "archetypeId" : {
      "@type" : "ARCHETYPE_HRID",
      "value" : "openEHR-EHR-CLUSTER.ovl-range_of_motion-001.v1"
    },
    "definition" : {
      "@type" : "C_COMPLEX_OBJECT",
      "rmTypeName" : "CLUSTER",
      "nodeId" : "at0000.1",
      "attributes" : [ {
        "@type" : "C_ATTRIBUTE",
        "rmAttributeName" : "items",
        "children" : [ {
          "@type" : "C_COMPLEX_OBJECT",
          "rmTypeName" : "ELEMENT",
          "occurrences" : "0..0",
          "nodeId" : "at0023.1",
          "attributes" : [ ],
          "attributeTuples" : [ ]
        }, {
          "@type" : "C_COMPLEX_OBJECT",
          "rmTypeName" : "ELEMENT",
          "occurrences" : "0..0",
          "nodeId" : "at0024.1",
          "attributes" : [ {
            "@type" : "C_ATTRIBUTE",
            "rmAttributeName" : "value",
            "children" : [ {
              "@type" : "C_COMPLEX_OBJECT",
              "rmTypeName" : "DV_CODED_TEXT",
              "attributes" : [ {
                "@type" : "C_ATTRIBUTE",
                "rmAttributeName" : "defining_code",
                "children" : [ {
                  "@type" : "C_TERMINOLOGY_CODE",
                  "rmTypeName" : "TERMINOLOGY_CODE",
                  "occurrences" : "1..1",
                  "terminologyId" : {
                    "value" : "local"
                  },
                  "constraint" : [ "ac0.1" ],
                  "selectedTerminologies" : [ ]
                } ]
              } ],
              "attributeTuples" : [ ]
            }, {
              "@type" : "C_COMPLEX_OBJECT",
              "rmTypeName" : "DV_TEXT",
              "attributes" : [ ],
              "attributeTuples" : [ ]
            } ]
          } ],
          "attributeTuples" : [ ]
        }, {
          "@type" : "C_COMPLEX_OBJECT",
          "rmTypeName" : "ELEMENT",
          "occurrences" : "0..0",
          "nodeId" : "at0027.1",
          "attributes" : [ {
            "@type" : "C_ATTRIBUTE",
            "rmAttributeName" : "value",
            "children" : [ {
              "@type" : "C_COMPLEX_OBJECT",
              "rmTypeName" : "DV_QUANTITY",
              "attributes" : [ ],
              "attributeTuples" : [ {
                "@type" : "C_ATTRIBUTE_TUPLE",
                "members" : [ {
                  "@type" : "C_ATTRIBUTE",
                  "rmAttributeName" : "units",
                  "children" : [ ]
                }, {
                  "@type" : "C_ATTRIBUTE",
                  "rmAttributeName" : "magnitude",
                  "children" : [ ]
                } ],
                "tuples" : [ {
                  "@type" : "C_PRIMITIVE_TUPLE",
                  "members" : [ {
                    "@type" : "C_STRING",
                    "rmTypeName" : "STRING",
                    "constraint" : [ "deg" ]
                  }, {
                    "@type" : "C_REAL",
                    "rmTypeName" : "REAL",
                    "constraint" : [ {
                      "lower" : -360.0,
                      "upper" : 360.0,
                      "lowerIncluded" : true,
                      "upperIncluded" : true,
                      "lowerUnbounded" : false,
                      "upperUnbounded" : false
                    } ]
                  } ]
                }, {
                  "@type" : "C_PRIMITIVE_TUPLE",
                  "members" : [ {
                    "@type" : "C_STRING",
                    "rmTypeName" : "STRING",
                    "constraint" : [ "mm" ]
                  }, {
                    "@type" : "C_REAL",
                    "rmTypeName" : "REAL",
                    "constraint" : [ {
                      "lowerIncluded" : false,
                      "upperIncluded" : false,
                      "lowerUnbounded" : true,
                      "upperUnbounded" : true
                    } ]
                  } ]
                }, {
                  "@type" : "C_PRIMITIVE_TUPLE",
                  "members" : [ {
                    "@type" : "C_STRING",
                    "rmTypeName" : "STRING",
                    "constraint" : [ "cm" ]
                  }, {
                    "@type" : "C_REAL",
                    "rmTypeName" : "REAL",
                    "constraint" : [ {
                      "lowerIncluded" : false,
                      "upperIncluded" : false,
                      "lowerUnbounded" : true,
                      "upperUnbounded" : true
                    } ]
                  } ]
                } ]
              } ]
            } ]
          } ],
          "attributeTuples" : [ ]
        }, {
          "@type" : "C_COMPLEX_OBJECT",
          "rmTypeName" : "ELEMENT",
          "occurrences" : "0..0",
          "nodeId" : "at0035.1",
          "attributes" : [ ],
          "attributeTuples" : [ ]
        }, {
          "@type" : "C_COMPLEX_OBJECT",
          "rmTypeName" : "ELEMENT",
          "occurrences" : "0..0",
          "nodeId" : "at0029.1",
          "attributes" : [ ],
          "attributeTuples" : [ ]
        } ]
      } ],
      "attributeTuples" : [ ]
    },
    "terminology" : {
      "@type" : "ARCHETYPE_TERMINOLOGY",
      "conceptCode" : "at0000",
      "termDefinitions" : {
        "en" : {
          "at0000.1" : {
            "@type" : "ARCHETYPE_TERM",
            "code" : "at0000.1",
            "text" : "Motion of a joint",
            "description" : "Measurement of the extent of motion for a specified simple or complex movement around an indentified joint or section of the spine."
          },
          "ac0.1" : {
            "@type" : "ARCHETYPE_TERM",
            "text" : "(Synthesized)",
            "code" : "ac0.1",
            "description" : ""
          }
        },
        "nb" : {
          "ac0.1" : {
            "@type" : "ARCHETYPE_TERM",
            "text" : "*(Synthesized) (en)",
            "code" : "ac0.1",
            "description" : ""
          }
        }
      },
      "termBindings" : { },
      "terminologyExtracts" : { },
      "valueSets" : {
        "ac0.1" : {
          "@type" : "VALUE_SET",
          "id" : "ac0.1",
          "members" : [ "at0025", "at0034", "at0026" ]
        }
      }
    },
    "adlVersion" : "1.4",
    "buildUid" : "9a6768f4-250f-4422-bfa5-20c0835b8c82",
    "rmName" : "openehr",
    "rmRelease" : "1.1.0",
    "generated" : true,
    "otherMetaData" : { },
    "originalLanguage" : {
      "terminologyId" : {
        "value" : "ISO_639-1"
      },
      "codeString" : "en"
    },
    "translations" : [ {
      "@type" : "TRANSLATION_DETAILS",
      "language" : {
        "terminologyId" : {
          "value" : "ISO_639-1"
        },
        "codeString" : "nb"
      },
      "author" : {
        "name" : "John Tore Valand, Hanne Marte Bårholm",
        "organisation" : "Helse Vest IKT",
        "email" : "john.tore.valand@helse-vest-ikt.no, hanne.marte.sandal.barholm@helse-vest-ikt.no"
      },
      "otherDetails" : { }
    } ]
  }, {
    "@type" : "TEMPLATE_OVERLAY",
    "uid" : "514e91dd-099b-4fb0-9f2d-3031d660c540",
    "description" : {
      "@type" : "RESOURCE_DESCRIPTION",
      "originalAuthor" : { },
      "otherContributors" : [ ],
      "ipAcknowledgements" : { },
      "references" : { },
      "conversionDetails" : { },
      "otherDetails" : {
        "PARENT:MD5-CAM-1.0.1" : "BBF04254F8BEA1421AF2CC97A0B64624"
      },
      "details" : { }
    },
    "parentArchetypeId" : "openEHR-EHR-CLUSTER.timing_daily.v1",
    "differential" : true,
    "archetypeId" : {
      "@type" : "ARCHETYPE_HRID",
      "value" : "openEHR-EHR-CLUSTER.ovl-timing_daily-001.v1"
    },
    "definition" : {
      "@type" : "C_COMPLEX_OBJECT",
      "rmTypeName" : "CLUSTER",
      "nodeId" : "at0000.1",
      "attributes" : [ {
        "@type" : "C_ATTRIBUTE",
        "rmAttributeName" : "items",
        "children" : [ {
          "@type" : "C_COMPLEX_OBJECT",
          "rmTypeName" : "ELEMENT",
          "occurrences" : "0..0",
          "nodeId" : "at0003.1",
          "attributes" : [ {
            "@type" : "C_ATTRIBUTE",
            "rmAttributeName" : "value",
            "children" : [ {
              "@type" : "C_COMPLEX_OBJECT",
              "rmTypeName" : "DV_QUANTITY",
              "attributes" : [ ],
              "attributeTuples" : [ {
                "@type" : "C_ATTRIBUTE_TUPLE",
                "members" : [ {
                  "@type" : "C_ATTRIBUTE",
                  "rmAttributeName" : "units",
                  "children" : [ ]
                }, {
                  "@type" : "C_ATTRIBUTE",
                  "rmAttributeName" : "magnitude",
                  "children" : [ ]
                }, {
                  "@type" : "C_ATTRIBUTE",
                  "rmAttributeName" : "precision",
                  "children" : [ ]
                } ],
                "tuples" : [ {
                  "@type" : "C_PRIMITIVE_TUPLE",
                  "members" : [ {
                    "@type" : "C_STRING",
                    "rmTypeName" : "STRING",
                    "constraint" : [ "1/d" ]
                  }, {
                    "@type" : "C_REAL",
                    "rmTypeName" : "REAL",
                    "constraint" : [ {
                      "lower" : 1.0,
                      "lowerIncluded" : true,
                      "upperIncluded" : false,
                      "lowerUnbounded" : false,
                      "upperUnbounded" : true
                    } ]
                  }, {
                    "@type" : "C_INTEGER",
                    "rmTypeName" : "INTEGER",
                    "constraint" : [ {
                      "lower" : 0,
                      "upper" : 0,
                      "lowerIncluded" : true,
                      "upperIncluded" : true,
                      "lowerUnbounded" : false,
                      "upperUnbounded" : false
                    } ]
                  } ]
                }, {
                  "@type" : "C_PRIMITIVE_TUPLE",
                  "members" : [ {
                    "@type" : "C_STRING",
                    "rmTypeName" : "STRING",
                    "constraint" : [ "1/min" ]
                  }, {
                    "@type" : "C_REAL",
                    "rmTypeName" : "REAL",
                    "constraint" : [ {
                      "lower" : 1.0,
                      "lowerIncluded" : true,
                      "upperIncluded" : false,
                      "lowerUnbounded" : false,
                      "upperUnbounded" : true
                    } ]
                  }, {
                    "@type" : "C_INTEGER",
                    "rmTypeName" : "INTEGER",
                    "constraint" : [ {
                      "lower" : 0,
                      "upper" : 0,
                      "lowerIncluded" : true,
                      "upperIncluded" : true,
                      "lowerUnbounded" : false,
                      "upperUnbounded" : false
                    } ]
                  } ]
                }, {
                  "@type" : "C_PRIMITIVE_TUPLE",
                  "members" : [ {
                    "@type" : "C_STRING",
                    "rmTypeName" : "STRING",
                    "constraint" : [ "1/s" ]
                  }, {
                    "@type" : "C_REAL",
                    "rmTypeName" : "REAL",
                    "constraint" : [ {
                      "lower" : 1.0,
                      "lowerIncluded" : true,
                      "upperIncluded" : false,
                      "lowerUnbounded" : false,
                      "upperUnbounded" : true
                    } ]
                  }, {
                    "@type" : "C_INTEGER",
                    "rmTypeName" : "INTEGER",
                    "constraint" : [ {
                      "lower" : 0,
                      "upper" : 0,
                      "lowerIncluded" : true,
                      "upperIncluded" : true,
                      "lowerUnbounded" : false,
                      "upperUnbounded" : false
                    } ]
                  } ]
                }, {
                  "@type" : "C_PRIMITIVE_TUPLE",
                  "members" : [ {
                    "@type" : "C_STRING",
                    "rmTypeName" : "STRING",
                    "constraint" : [ "1/h" ]
                  }, {
                    "@type" : "C_REAL",
                    "rmTypeName" : "REAL",
                    "constraint" : [ {
                      "lower" : 1.0,
                      "lowerIncluded" : true,
                      "upperIncluded" : false,
                      "lowerUnbounded" : false,
                      "upperUnbounded" : true
                    } ]
                  }, {
                    "@type" : "C_INTEGER",
                    "rmTypeName" : "INTEGER",
                    "constraint" : [ {
                      "lower" : 0,
                      "upper" : 0,
                      "lowerIncluded" : true,
                      "upperIncluded" : true,
                      "lowerUnbounded" : false,
                      "upperUnbounded" : false
                    } ]
                  } ]
                } ]
              } ]
            }, {
              "@type" : "C_COMPLEX_OBJECT",
              "rmTypeName" : "DV_INTERVAL<DV_QUANTITY>",
              "attributes" : [ {
                "@type" : "C_ATTRIBUTE",
                "rmAttributeName" : "lower",
                "children" : [ {
                  "@type" : "C_COMPLEX_OBJECT",
                  "rmTypeName" : "DV_QUANTITY",
                  "attributes" : [ ],
                  "attributeTuples" : [ {
                    "@type" : "C_ATTRIBUTE_TUPLE",
                    "members" : [ {
                      "@type" : "C_ATTRIBUTE",
                      "rmAttributeName" : "units",
                      "children" : [ ]
                    }, {
                      "@type" : "C_ATTRIBUTE",
                      "rmAttributeName" : "magnitude",
                      "children" : [ ]
                    }, {
                      "@type" : "C_ATTRIBUTE",
                      "rmAttributeName" : "precision",
                      "children" : [ ]
                    } ],
                    "tuples" : [ {
                      "@type" : "C_PRIMITIVE_TUPLE",
                      "members" : [ {
                        "@type" : "C_STRING",
                        "rmTypeName" : "STRING",
                        "constraint" : [ "1/d" ]
                      }, {
                        "@type" : "C_REAL",
                        "rmTypeName" : "REAL",
                        "constraint" : [ {
                          "lower" : 1.0,
                          "lowerIncluded" : true,
                          "upperIncluded" : false,
                          "lowerUnbounded" : false,
                          "upperUnbounded" : true
                        } ]
                      }, {
                        "@type" : "C_INTEGER",
                        "rmTypeName" : "INTEGER",
                        "constraint" : [ {
                          "lower" : 0,
                          "upper" : 0,
                          "lowerIncluded" : true,
                          "upperIncluded" : true,
                          "lowerUnbounded" : false,
                          "upperUnbounded" : false
                        } ]
                      } ]
                    }, {
                      "@type" : "C_PRIMITIVE_TUPLE",
                      "members" : [ {
                        "@type" : "C_STRING",
                        "rmTypeName" : "STRING",
                        "constraint" : [ "1/min" ]
                      }, {
                        "@type" : "C_REAL",
                        "rmTypeName" : "REAL",
                        "constraint" : [ {
                          "lower" : 1.0,
                          "lowerIncluded" : true,
                          "upperIncluded" : false,
                          "lowerUnbounded" : false,
                          "upperUnbounded" : true
                        } ]
                      }, {
                        "@type" : "C_INTEGER",
                        "rmTypeName" : "INTEGER",
                        "constraint" : [ {
                          "lower" : 0,
                          "upper" : 0,
                          "lowerIncluded" : true,
                          "upperIncluded" : true,
                          "lowerUnbounded" : false,
                          "upperUnbounded" : false
                        } ]
                      } ]
                    }, {
                      "@type" : "C_PRIMITIVE_TUPLE",
                      "members" : [ {
                        "@type" : "C_STRING",
                        "rmTypeName" : "STRING",
                        "constraint" : [ "1/s" ]
                      }, {
                        "@type" : "C_REAL",
                        "rmTypeName" : "REAL",
                        "constraint" : [ {
                          "lower" : 1.0,
                          "lowerIncluded" : true,
                          "upperIncluded" : false,
                          "lowerUnbounded" : false,
                          "upperUnbounded" : true
                        } ]
                      }, {
                        "@type" : "C_INTEGER",
                        "rmTypeName" : "INTEGER",
                        "constraint" : [ {
                          "lower" : 0,
                          "upper" : 0,
                          "lowerIncluded" : true,
                          "upperIncluded" : true,
                          "lowerUnbounded" : false,
                          "upperUnbounded" : false
                        } ]
                      } ]
                    }, {
                      "@type" : "C_PRIMITIVE_TUPLE",
                      "members" : [ {
                        "@type" : "C_STRING",
                        "rmTypeName" : "STRING",
                        "constraint" : [ "1/h" ]
                      }, {
                        "@type" : "C_REAL",
                        "rmTypeName" : "REAL",
                        "constraint" : [ {
                          "lower" : 1.0,
                          "lowerIncluded" : true,
                          "upperIncluded" : false,
                          "lowerUnbounded" : false,
                          "upperUnbounded" : true
                        } ]
                      }, {
                        "@type" : "C_INTEGER",
                        "rmTypeName" : "INTEGER",
                        "constraint" : [ {
                          "lower" : 0,
                          "upper" : 0,
                          "lowerIncluded" : true,
                          "upperIncluded" : true,
                          "lowerUnbounded" : false,
                          "upperUnbounded" : false
                        } ]
                      } ]
                    } ]
                  } ]
                } ]
              }, {
                "@type" : "C_ATTRIBUTE",
                "rmAttributeName" : "upper",
                "children" : [ {
                  "@type" : "C_COMPLEX_OBJECT",
                  "rmTypeName" : "DV_QUANTITY",
                  "attributes" : [ ],
                  "attributeTuples" : [ {
                    "@type" : "C_ATTRIBUTE_TUPLE",
                    "members" : [ {
                      "@type" : "C_ATTRIBUTE",
                      "rmAttributeName" : "units",
                      "children" : [ ]
                    }, {
                      "@type" : "C_ATTRIBUTE",
                      "rmAttributeName" : "magnitude",
                      "children" : [ ]
                    }, {
                      "@type" : "C_ATTRIBUTE",
                      "rmAttributeName" : "precision",
                      "children" : [ ]
                    } ],
                    "tuples" : [ {
                      "@type" : "C_PRIMITIVE_TUPLE",
                      "members" : [ {
                        "@type" : "C_STRING",
                        "rmTypeName" : "STRING",
                        "constraint" : [ "1/d" ]
                      }, {
                        "@type" : "C_REAL",
                        "rmTypeName" : "REAL",
                        "constraint" : [ {
                          "lower" : 1.0,
                          "lowerIncluded" : true,
                          "upperIncluded" : false,
                          "lowerUnbounded" : false,
                          "upperUnbounded" : true
                        } ]
                      }, {
                        "@type" : "C_INTEGER",
                        "rmTypeName" : "INTEGER",
                        "constraint" : [ {
                          "lower" : 0,
                          "upper" : 0,
                          "lowerIncluded" : true,
                          "upperIncluded" : true,
                          "lowerUnbounded" : false,
                          "upperUnbounded" : false
                        } ]
                      } ]
                    }, {
                      "@type" : "C_PRIMITIVE_TUPLE",
                      "members" : [ {
                        "@type" : "C_STRING",
                        "rmTypeName" : "STRING",
                        "constraint" : [ "1/min" ]
                      }, {
                        "@type" : "C_REAL",
                        "rmTypeName" : "REAL",
                        "constraint" : [ {
                          "lower" : 1.0,
                          "lowerIncluded" : true,
                          "upperIncluded" : false,
                          "lowerUnbounded" : false,
                          "upperUnbounded" : true
                        } ]
                      }, {
                        "@type" : "C_INTEGER",
                        "rmTypeName" : "INTEGER",
                        "constraint" : [ {
                          "lower" : 0,
                          "upper" : 0,
                          "lowerIncluded" : true,
                          "upperIncluded" : true,
                          "lowerUnbounded" : false,
                          "upperUnbounded" : false
                        } ]
                      } ]
                    }, {
                      "@type" : "C_PRIMITIVE_TUPLE",
                      "members" : [ {
                        "@type" : "C_STRING",
                        "rmTypeName" : "STRING",
                        "constraint" : [ "1/s" ]
                      }, {
                        "@type" : "C_REAL",
                        "rmTypeName" : "REAL",
                        "constraint" : [ {
                          "lower" : 1.0,
                          "lowerIncluded" : true,
                          "upperIncluded" : false,
                          "lowerUnbounded" : false,
                          "upperUnbounded" : true
                        } ]
                      }, {
                        "@type" : "C_INTEGER",
                        "rmTypeName" : "INTEGER",
                        "constraint" : [ {
                          "lower" : 0,
                          "upper" : 0,
                          "lowerIncluded" : true,
                          "upperIncluded" : true,
                          "lowerUnbounded" : false,
                          "upperUnbounded" : false
                        } ]
                      } ]
                    }, {
                      "@type" : "C_PRIMITIVE_TUPLE",
                      "members" : [ {
                        "@type" : "C_STRING",
                        "rmTypeName" : "STRING",
                        "constraint" : [ "1/h" ]
                      }, {
                        "@type" : "C_REAL",
                        "rmTypeName" : "REAL",
                        "constraint" : [ {
                          "lower" : 1.0,
                          "lowerIncluded" : true,
                          "upperIncluded" : false,
                          "lowerUnbounded" : false,
                          "upperUnbounded" : true
                        } ]
                      }, {
                        "@type" : "C_INTEGER",
                        "rmTypeName" : "INTEGER",
                        "constraint" : [ {
                          "lower" : 0,
                          "upper" : 0,
                          "lowerIncluded" : true,
                          "upperIncluded" : true,
                          "lowerUnbounded" : false,
                          "upperUnbounded" : false
                        } ]
                      } ]
                    } ]
                  } ]
                } ]
              } ],
              "attributeTuples" : [ ]
            } ]
          } ],
          "attributeTuples" : [ ]
        }, {
          "@type" : "C_COMPLEX_OBJECT",
          "rmTypeName" : "ELEMENT",
          "occurrences" : "0..0",
          "nodeId" : "at0014.1",
          "attributes" : [ {
            "@type" : "C_ATTRIBUTE",
            "rmAttributeName" : "value",
            "children" : [ {
              "@type" : "C_COMPLEX_OBJECT",
              "rmTypeName" : "DV_DURATION",
              "attributes" : [ {
                "@type" : "C_ATTRIBUTE",
                "rmAttributeName" : "value",
                "children" : [ {
                  "@type" : "C_DURATION",
                  "rmTypeName" : "DURATION",
                  "occurrences" : "1..1",
                  "patternedConstraint" : "PTHMS",
                  "constraint" : [ {
                    "lower" : "PT0S",
                    "upper" : "PT24H",
                    "lowerIncluded" : true,
                    "upperIncluded" : true,
                    "lowerUnbounded" : false,
                    "upperUnbounded" : false
                  } ]
                } ]
              } ],
              "attributeTuples" : [ ]
            } ]
          } ],
          "attributeTuples" : [ ]
        }, {
          "@type" : "C_COMPLEX_OBJECT",
          "rmTypeName" : "ELEMENT",
          "occurrences" : "0..0",
          "nodeId" : "at0004.1",
          "attributes" : [ {
            "@type" : "C_ATTRIBUTE",
            "rmAttributeName" : "value",
            "children" : [ {
              "@type" : "C_COMPLEX_OBJECT",
              "rmTypeName" : "DV_TIME",
              "attributes" : [ ],
              "attributeTuples" : [ ]
            }, {
              "@type" : "C_COMPLEX_OBJECT",
              "rmTypeName" : "DV_INTERVAL<DV_TIME>",
              "attributes" : [ ],
              "attributeTuples" : [ ]
            } ]
          } ],
          "attributeTuples" : [ ]
        }, {
          "@type" : "C_COMPLEX_OBJECT",
          "rmTypeName" : "ELEMENT",
          "occurrences" : "0..0",
          "nodeId" : "at0027.1",
          "attributes" : [ ],
          "attributeTuples" : [ ]
        }, {
          "@type" : "C_COMPLEX_OBJECT",
          "rmTypeName" : "ELEMENT",
          "occurrences" : "0..0",
          "nodeId" : "at0023.1",
          "attributes" : [ {
            "@type" : "C_ATTRIBUTE",
            "rmAttributeName" : "value",
            "children" : [ {
              "@type" : "C_COMPLEX_OBJECT",
              "rmTypeName" : "DV_BOOLEAN",
              "attributes" : [ ],
              "attributeTuples" : [ ]
            } ]
          } ],
          "attributeTuples" : [ ]
        }, {
          "@type" : "C_COMPLEX_OBJECT",
          "rmTypeName" : "ELEMENT",
          "occurrences" : "0..0",
          "nodeId" : "at0024.1",
          "attributes" : [ {
            "@type" : "C_ATTRIBUTE",
            "rmAttributeName" : "value",
            "children" : [ {
              "@type" : "C_COMPLEX_OBJECT",
              "rmTypeName" : "DV_BOOLEAN",
              "attributes" : [ {
                "@type" : "C_ATTRIBUTE",
                "rmAttributeName" : "value",
                "children" : [ {
                  "@type" : "C_BOOLEAN",
                  "rmTypeName" : "BOOLEAN",
                  "occurrences" : "1..1",
                  "constraint" : [ true ]
                } ]
              } ],
              "attributeTuples" : [ ]
            } ]
          } ],
          "attributeTuples" : [ ]
        }, {
          "@type" : "C_COMPLEX_OBJECT",
          "rmTypeName" : "ELEMENT",
          "occurrences" : "0..0",
          "nodeId" : "at0025.1",
          "attributes" : [ ],
          "attributeTuples" : [ ]
        }, {
          "@type" : "C_COMPLEX_OBJECT",
          "rmTypeName" : "CLUSTER",
          "nodeId" : "at0039",
          "attributes" : [ {
            "@type" : "C_ATTRIBUTE",
            "rmAttributeName" : "items",
            "children" : [ {
              "@type" : "C_COMPLEX_OBJECT",
              "rmTypeName" : "ELEMENT",
              "nodeId" : "at0026.1",
              "attributes" : [ {
                "@type" : "C_ATTRIBUTE",
                "rmAttributeName" : "value",
                "children" : [ {
                  "@type" : "C_COMPLEX_OBJECT",
                  "rmTypeName" : "DV_CODED_TEXT",
                  "occurrences" : "1..1",
                  "attributes" : [ {
                    "@type" : "C_ATTRIBUTE",
                    "rmAttributeName" : "defining_code",
                    "children" : [ {
                      "@type" : "C_TERMINOLOGY_CODE",
                      "rmTypeName" : "TERMINOLOGY_CODE",
                      "occurrences" : "0..1",
                      "terminologyId" : {
                        "value" : "SNOMED-CT"
                      },
                      "constraint" : [ ],
                      "selectedTerminologies" : [ "SNOMED-CT" ],
                      "includedExternalTerminologyCodes" : [ {
                        "terminologyId" : "SNOMED-CT",
                        "code" : "421355008",
                        "value" : "Awakening"
                      }, {
                        "terminologyId" : "SNOMED-CT",
                        "code" : "73775008",
                        "value" : "Morning"
                      }, {
                        "terminologyId" : "SNOMED-CT",
                        "code" : "422133006",
                        "value" : "Afternoon"
                      }, {
                        "terminologyId" : "SNOMED-CT",
                        "code" : "3157002",
                        "value" : "Evening"
                      }, {
                        "terminologyId" : "SNOMED-CT",
                        "code" : "2546009",
                        "value" : "Night time"
                      } ]
                    } ]
                  } ],
                  "attributeTuples" : [ ]
                } ]
              } ],
              "attributeTuples" : [ ]
            }, {
              "@type" : "C_COMPLEX_OBJECT",
              "rmTypeName" : "ELEMENT",
              "occurrences" : "0..0",
              "nodeId" : "at0040.1",
              "attributes" : [ {
                "@type" : "C_ATTRIBUTE",
                "rmAttributeName" : "value",
                "children" : [ {
                  "@type" : "C_COMPLEX_OBJECT",
                  "rmTypeName" : "DV_DURATION",
                  "attributes" : [ {
                    "@type" : "C_ATTRIBUTE",
                    "rmAttributeName" : "value",
                    "children" : [ {
                      "@type" : "C_DURATION",
                      "rmTypeName" : "DURATION",
                      "occurrences" : "1..1",
                      "patternedConstraint" : "PTHMS",
                      "constraint" : [ {
                        "lower" : "PT0S",
                        "upper" : "PT24H",
                        "lowerIncluded" : true,
                        "upperIncluded" : true,
                        "lowerUnbounded" : false,
                        "upperUnbounded" : false
                      } ]
                    } ]
                  } ],
                  "attributeTuples" : [ ]
                } ]
              } ],
              "attributeTuples" : [ ]
            } ]
          } ],
          "attributeTuples" : [ ]
        }, {
          "@type" : "C_COMPLEX_OBJECT",
          "rmTypeName" : "CLUSTER",
          "occurrences" : "0..0",
          "nodeId" : "at0035.1",
          "attributes" : [ ],
          "attributeTuples" : [ ]
        } ]
      } ],
      "attributeTuples" : [ ]
    },
    "terminology" : {
      "@type" : "ARCHETYPE_TERMINOLOGY",
      "conceptCode" : "at0000",
      "termDefinitions" : {
        "en" : { },
        "sl" : { },
        "nb" : { },
        "de" : { }
      },
      "termBindings" : { },
      "terminologyExtracts" : { },
      "valueSets" : { }
    },
    "adlVersion" : "1.4",
    "buildUid" : "319e2df4-1bec-49a3-bbab-6b8a0e5bc218",
    "rmName" : "openehr",
    "rmRelease" : "1.1.0",
    "generated" : true,
    "otherMetaData" : { },
    "originalLanguage" : {
      "terminologyId" : {
        "value" : "ISO_639-1"
      },
      "codeString" : "en"
    },
    "translations" : [ {
      "@type" : "TRANSLATION_DETAILS",
      "language" : {
        "terminologyId" : {
          "value" : "ISO_639-1"
        },
        "codeString" : "de"
      },
      "author" : {
        "name" : "Caroline Bönisch, Natalia Strauch",
        "organisation" : "UMG, Medizinische Hochschule Hannover",
        "email" : "Caroline.Thoms@med.uni-goettingen.de, Strauch.Natalia@mh-hannover.de"
      },
      "otherDetails" : { }
    }, {
      "@type" : "TRANSLATION_DETAILS",
      "language" : {
        "terminologyId" : {
          "value" : "ISO_639-1"
        },
        "codeString" : "nb"
      },
      "author" : {
        "name" : "Silje Ljosland Bakke",
        "organisation" : "Nasjonal IKT HF"
      },
      "otherDetails" : { }
    }, {
      "@type" : "TRANSLATION_DETAILS",
      "language" : {
        "terminologyId" : {
          "value" : "ISO_639-1"
        },
        "codeString" : "sl"
      },
      "author" : {
        "name" : "?"
      },
      "otherDetails" : { }
    } ]
  } ],
  "originalLanguage" : {
    "terminologyId" : {
      "value" : "ISO_639-1"
    },
    "codeString" : "en"
  },
  "translations" : [ {
    "@type" : "TRANSLATION_DETAILS",
    "language" : {
      "terminologyId" : {
        "value" : "ISO_639-1"
      },
      "codeString" : "nn"
    },
    "author" : { },
    "otherDetails" : { }
  }, {
    "@type" : "TRANSLATION_DETAILS",
    "language" : {
      "terminologyId" : {
        "value" : "ISO_639-1"
      },
      "codeString" : "de"
    },
    "author" : { },
    "otherDetails" : { }
  }, {
    "@type" : "TRANSLATION_DETAILS",
    "language" : {
      "terminologyId" : {
        "value" : "ISO_639-1"
      },
      "codeString" : "sv"
    },
    "author" : { },
    "otherDetails" : { }
  }, {
    "@type" : "TRANSLATION_DETAILS",
    "language" : {
      "terminologyId" : {
        "value" : "ISO_639-1"
      },
      "codeString" : "nb"
    },
    "author" : { },
    "otherDetails" : { }
  }, {
    "@type" : "TRANSLATION_DETAILS",
    "language" : {
      "terminologyId" : {
        "value" : "ISO_639-1"
      },
      "codeString" : "pt"
    },
    "author" : { },
    "otherDetails" : { }
  }, {
    "@type" : "TRANSLATION_DETAILS",
    "language" : {
      "terminologyId" : {
        "value" : "ISO_639-1"
      },
      "codeString" : "fr"
    },
    "author" : { },
    "otherDetails" : { }
  } ]
}